geotask/__init__.py
geotask/common.py
geotask/foliummap.py
geotask/geotask.py
geotask/temp.py
geotask/utils.py
geotask-0.0.6.dist-info/LICENSE
geotask-0.0.6.dist-info/METADATA
geotask-0.0.6.dist-info/WHEEL
geotask-0.0.6.dist-info/entry_points.txt
geotask-0.0.6.dist-info/top_level.txt
geotask-0.0.6.dist-info/RECORD
