Metadata-Version: 2.1
Name: geotask
Version: 0.0.6
Summary: A demo python package
Author-email: Syeda Nazifa Tasneem <nazifadu.g57@gmail.com>
License: MIT License
Project-URL: Homepage, https://github.com/nazifa02/geotask
Keywords: geotask
Classifier: Intended Audience :: Developers
Classifier: License :: OSI Approved :: MIT License
Classifier: Natural Language :: English
Classifier: Programming Language :: Python :: 3.8
Classifier: Programming Language :: Python :: 3.9
Classifier: Programming Language :: Python :: 3.10
Classifier: Programming Language :: Python :: 3.11
Classifier: Programming Language :: Python :: 3.12
Requires-Python: >=3.8
License-File: LICENSE
Requires-Dist: ipyleaflet
Requires-Dist: numpy
Requires-Dist: pandas
Requires-Dist: pyshp
Requires-Dist: geopandas
Requires-Dist: localtileserver
Requires-Dist: leafmap
Requires-Dist: xarray
Requires-Dist: imageio
Requires-Dist: ipywidgets
Requires-Dist: requests
Requires-Dist: folium
Requires-Dist: matplotlib
Requires-Dist: IPython
Provides-Extra: all
Requires-Dist: geotask[extra] ; extra == 'all'
Provides-Extra: extra
Requires-Dist: pandas ; extra == 'extra'
